LICENSE
README.rst
setup.py
pens/__init__.py
pens/ens.py
pens/utils.py
pens/visual.py
pens.egg-info/PKG-INFO
pens.egg-info/SOURCES.txt
pens.egg-info/dependency_links.txt
pens.egg-info/not-zip-safe
pens.egg-info/requires.txt
pens.egg-info/top_level.txt