Metadata-Version: 2.1
Name: pens
Version: 0.0.3
Summary: pens: utilities for comparing paleoclimate reconstruction ensembles
Home-page: https://github.com/fzhu2e/pens
Author: Feng Zhu
Author-email: fzhu@nuist.edu.cn
License: GPL 3.0 license
Keywords: paleocliamte reconstruction ensembles
Platform: UNKNOWN
Classifier: Natural Language :: English
Classifier: Programming Language :: Python :: 3.8
License-File: LICENSE
